Metadata-Version: 2.1
Name: phonemes2ids
Version: 1.2.2
Summary: Convert phonemes to integer ids
Home-page: https://github.com/rhasspy/phonemes2ids
Author: Michael Hansen
Author-email: mike@rhasspy.org
License: UNKNOWN
Platform: UNKNOWN
Classifier: Programming Language :: Python :: 3
Classifier: Programming Language :: Python :: 3.7
Classifier: Programming Language :: Python :: 3.8
Classifier: License :: OSI Approved :: MIT License
